clat/__init__.py
clat/compile/__init__.py
clat/compile/task/__init__.py
clat/compile/task/base_database_fields.py
clat/compile/task/cached_task_fields.py
clat/compile/task/classic_database_task_fields.py
clat/compile/task/compile_task_id.py
clat/compile/task/julie_database_fields.py
clat/compile/task/julie_intan_file_per_experiment_fields.py
clat/compile/task/julie_intan_file_per_trial_fields.py
clat/compile/task/matchstick_fields.py
clat/compile/task/task_field.py
clat/compile/trial/__init__.py
clat/compile/trial/cached_fields.py
clat/compile/trial/classic_database_fields.py
clat/compile/trial/matchstick_fields.py
clat/compile/trial/nafc_database_fields.py
clat/compile/trial/psychometric_compile.py
clat/compile/trial/trial_collector.py
clat/compile/trial/trial_field.py
clat/compile/tstamp/__init__.py
clat/compile/tstamp/cached_tstamp_fields.py
clat/compile/tstamp/classic_database_tstamp_fields.py
clat/compile/tstamp/trial_tstamp_collector.py
clat/compile/tstamp/tstamp_field.py
clat/eyecal/__init__.py
clat/eyecal/apply_eyecal.py
clat/eyecal/params.py
clat/eyecal/plot_eyecal.py
clat/intan/__init__.py
clat/intan/amplifiers.py
clat/intan/analogin.py
clat/intan/channels.py
clat/intan/livenotes.py
clat/intan/marker_channels.py
clat/intan/one_file_spike_parsing.py
clat/intan/response_processing.py
clat/intan/spike_file.py
clat/intan/spike_parsing.py
clat/intan/stitch.py
clat/intan/test_analogin.py
clat/intan/rhd/__init__.py
clat/intan/rhd/load_intan_rhd_format.py
clat/intan/rhd/intanutil/__init__.py
clat/intan/rhd/intanutil/data_to_result.py
clat/intan/rhd/intanutil/get_bytes_per_data_block.py
clat/intan/rhd/intanutil/notch_filter.py
clat/intan/rhd/intanutil/qstring.py
clat/intan/rhd/intanutil/read_header.py
clat/intan/rhd/intanutil/read_one_data_block.py
clat/pipeline/__init__.py
clat/pipeline/pipeline_base_classes.py
clat/util/__init__.py
clat/util/connection.py
clat/util/dictionary_util.py
clat/util/table_util.py
clat/util/time_util.py
intan/__init__.py
ConnorLabAnalysisTools-1.0.2.dist-info/METADATA
ConnorLabAnalysisTools-1.0.2.dist-info/WHEEL
ConnorLabAnalysisTools-1.0.2.dist-info/top_level.txt
ConnorLabAnalysisTools-1.0.2.dist-info/RECORD
